shipping/__init__.py
shipping/admin.py
shipping/beautifulsoup.py
shipping/codes.py
shipping/core.py
shipping/correios.py
shipping/email.py
shipping/fretefacil.py
shipping/hooks.py
shipping/models.py
shipping/tracking.py
shipping/urls.py
shipping/views.py
shipping/migrations/0001_initial.py
shipping/migrations/__init__.py
django_ship-0.2.7.dist-info/LICENSE
django_ship-0.2.7.dist-info/METADATA
django_ship-0.2.7.dist-info/WHEEL
django_ship-0.2.7.dist-info/top_level.txt
django_ship-0.2.7.dist-info/RECORD
